{
  "users": [
    {
      "id": "1001",
      "name": "Yingisani",
      "emailAddress": "yingi@skycode.co.za",
      "password": "_123.@yingi"
    },
    {
      "id": "1002",
      "name": "Sibongiseni",
      "emailAddress": "Sibongiseni@gmail.com",
      "password": "_123.@sibo"
    },
    {
      "id": "1003",
      "name": "Reinette",
      "emailAddress": "reinette@yahoo.com",
      "password": "_123.@reinette"
    },
    {
      "id": "1004",
      "name": "Tebogo",
      "emailAddress": "tebogo@skycode.co.za",
      "password": "_123.@tebogo"
    },
    {
      "id": "ad94",
      "name": "Jame",
      "emailAddress": "jbanda@mtn.co.za",
      "password": "somepassword"
    },
    {
      "id": "af09",
      "name": "Test",
      "emailAddress": "test@gmail.com",
      "password": "123456789"
    },
    {
      "id": "2e19",
      "name": "Tester",
      "emailAddress": "tester@test.co.za",
      "password": "tester@test.co.za"
    },
    {
      "id": "7b5b",
      "name": "Tested",
      "emailAddress": "tested@testing.co.za",
      "password": "tested@testing.co.za"
    },
    {
      "id": "2aed",
      "name": "reg",
      "emailAddress": "reg@reg.co.za",
      "password": "reg@reg.co.za"
    },
    {
      "id": "edc3",
      "name": "again",
      "emailAddress": "again@gmail.com",
      "password": "again@gmail.com"
    },
    {
      "id": "d68c",
      "name": "working",
      "emailAddress": "working@gmao.com",
      "password": "working@gmao.com"
    },
    {
      "id": "5f9c",
      "name": "Tincky",
      "emailAddress": "popeye@w.com",
      "password": "popeye@w.com"
    }
  ],
  "loginAttemps": [
    {
      "userId": 1003,
      "passedAttemps": {
        "sunday": 3,
        "monday": 2,
        "tuesday": 5,
        "wednesday": 1,
        "thursday": 4,
        "friday": 2,
        "saturday": 3
      },
      "failedAttemps": {
        "sunday": 2,
        "monday": 3,
        "tuesday": 3,
        "wednesday": 2,
        "thursday": 1,
        "friday": 4,
        "saturday": 1
      },
      "id": "47a3"
    },
    {
      "userId": 1001,
      "passedAttemps": {
        "sunday": 1,
        "monday": 4,
        "tuesday": 2,
        "wednesday": 2,
        "thursday": 1,
        "friday": 3,
        "saturday": 1
      },
      "failedAttemps": {
        "sunday": 4,
        "monday": 2,
        "tuesday": 4,
        "wednesday": 1,
        "thursday": 1,
        "friday": 3,
        "saturday": 3
      },
      "id": "c05a"
    },
    {
      "userId": 1004,
      "passedAttemps": {
        "sunday": 2,
        "monday": 1,
        "tuesday": 1,
        "wednesday": 1,
        "thursday": 3,
        "friday": 2,
        "saturday": 2
      },
      "failedAttemps": {
        "sunday": 1,
        "monday": 1,
        "tuesday": 2,
        "wednesday": 2,
        "thursday": 3,
        "friday": 1,
        "saturday": 1
      },
      "id": "e347"
    },
    {
      "userId": 1002,
      "passedAttemps": {
        "sunday": 1,
        "monday": 4,
        "tuesday": 2,
        "wednesday": 2,
        "thursday": 1,
        "friday": 3,
        "saturday": 3
      },
      "failedAttemps": {
        "sunday": 4,
        "monday": 2,
        "tuesday": 4,
        "wednesday": 1,
        "thursday": 1,
        "friday": 3,
        "saturday": 3
      },
      "id": "5770"
    }
  ]
}